line_notify/__init__.py
line_notify/image_utils.py
line_notify/line_notify.py
pyline_notify-0.0.6.dist-info/LICENSE
pyline_notify-0.0.6.dist-info/METADATA
pyline_notify-0.0.6.dist-info/WHEEL
pyline_notify-0.0.6.dist-info/top_level.txt
pyline_notify-0.0.6.dist-info/RECORD
