Metadata-Version: 2.1
Name: pyline-notify
Version: 0.0.6
Summary: A python library for manipulating line notify api
Home-page: https://github.com/iory/pyline-notify
Author: iory
Author-email: ab.ioryz@gmail.com
License: MIT
Platform: UNKNOWN
Classifier: Development Status :: 5 - Production/Stable
Classifier: Intended Audience :: Developers
Classifier: Natural Language :: English
Classifier: License :: OSI Approved :: MIT License
Classifier: Programming Language :: Python
Classifier: Programming Language :: Python :: 2.7
Classifier: Programming Language :: Python :: 3.5
Classifier: Programming Language :: Python :: 3.6
Classifier: Programming Language :: Python :: 3.7
Classifier: Programming Language :: Python :: Implementation :: CPython
License-File: LICENSE
Requires-Dist: numpy
Requires-Dist: pillow
Requires-Dist: requests
Requires-Dist: pathlib ; python_version < "3.0"
